ontosunburst/__init__.py
ontosunburst/commands.py
ontosunburst/dag2tree.py
ontosunburst/onto2dag.py
ontosunburst/ontosunburst.py
ontosunburst/tree2sunburst.py
ontosunburst/Inputs/chebi__239__classes.json
ontosunburst/Inputs/chebi__239__labels.json
ontosunburst/Inputs/chebi_r__239__classes.json
ontosunburst/Inputs/chebi_r__239__labels.json
ontosunburst/Inputs/ec__05feb25__classes.json
ontosunburst/Inputs/ec__05feb25__labels.json
ontosunburst/Inputs/go_bp__06feb25__classes.json
ontosunburst/Inputs/go_bp__06feb25__labels.json
ontosunburst/Inputs/go_cc__06feb25__classes.json
ontosunburst/Inputs/go_cc__06feb25__labels.json
ontosunburst/Inputs/go_mf__06feb25__classes.json
ontosunburst/Inputs/go_mf__06feb25__labels.json
ontosunburst/Inputs/kegg__113-0__classes.json
ontosunburst/Inputs/metacyc__26-0__classes.json
ontosunburst/Inputs_generation/gen_onto_files.py
ontosunburst/Inputs_generation/Input_files/enzclass.txt
ontosunburst/Inputs_generation/Input_files/enzyme.dat
ontosunburst/Inputs_generation/Input_files/metacyc_26.0_prot70.padmet
ontosunburst/Inputs_generation/Input_files/rhea-relationships_137.tsv
ontosunburst-0.1.1.dist-info/METADATA
ontosunburst-0.1.1.dist-info/WHEEL
ontosunburst-0.1.1.dist-info/entry_points.txt
ontosunburst-0.1.1.dist-info/licenses/LICENSE
ontosunburst-0.1.1.dist-info/RECORD
