Metadata-Version: 2.4
Name: ontosunburst
Version: 0.1.1
Summary: Sunbursts for ontologies
Project-URL: Homepage, https://github.com/AuReMe/Ontology_sunburst.git
Project-URL: Documentation, https://github.com/AuReMe/Ontosunburst/wiki
Project-URL: Repository, https://github.com/AuReMe/Ontology_sunburst.git
Author-email: Pauline Hamon-Giraud <pauline.hamongiraud@gmail.com>, AuReMe <gem-aureme@inria.fr>
Maintainer-email: Pauline Hamon-Giraud <pauline.hamongiraud@gmail.com>
License:                     GNU GENERAL PUBLIC LICENSE
License-File: LICENSE
Keywords: chebi,enrichment,gene ontology,ontology,sunburst,tree,visualisation
Classifier: Development Status :: 3 - Alpha
Classifier: Intended Audience :: Science/Research
Classifier: Operating System :: Unix
Classifier: Programming Language :: Python :: 3.10
Classifier: Topic :: Scientific/Engineering :: Bio-Informatics
Requires-Python: >=3.10
Requires-Dist: numpy>=1.26.1
Requires-Dist: pandas>=1.5.3
Requires-Dist: plotly>=5.17.0
Requires-Dist: scipy>=1.11.3
